fb2reader/__init__.py
fb2reader/fb2reader.py
fb2reader-1.0.4.dist-info/licenses/LICENSE
fb2reader-1.0.4.dist-info/METADATA
fb2reader-1.0.4.dist-info/WHEEL
fb2reader-1.0.4.dist-info/top_level.txt
fb2reader-1.0.4.dist-info/RECORD
