Metadata-Version: 2.4
Name: fb2reader
Version: 1.0.4
Summary: A Python library for extracting data and metadata from FB2 (FictionBook 2) format files
Author-email: Roman Kudryavskyi <devpilgrim@gmail.com>
Project-URL: Homepage, https://github.com/devpilgrin/fb2reader
Project-URL: Documentation, https://github.com/devpilgrin/fb2reader#readme
Project-URL: Repository, https://github.com/devpilgrin/fb2reader
Project-URL: Bug Reports, https://github.com/devpilgrin/fb2reader/issues
Keywords: ebook,metadata,fb2,fictionbook,parser,reader
Classifier: Development Status :: 4 - Beta
Classifier: Intended Audience :: Developers
Classifier: License :: OSI Approved :: Apache Software License
Classifier: Operating System :: OS Independent
Classifier: Programming Language :: Python :: 3
Classifier: Programming Language :: Python :: 3.8
Classifier: Programming Language :: Python :: 3.9
Classifier: Programming Language :: Python :: 3.10
Classifier: Programming Language :: Python :: 3.11
Classifier: Programming Language :: Python :: 3.12
Classifier: Topic :: Software Development :: Libraries :: Python Modules
Classifier: Topic :: Text Processing :: Markup :: XML
Classifier: Typing :: Typed
Requires-Python: >=3.8
License-File: LICENSE
Requires-Dist: beautifulsoup4>=4.9.0
Requires-Dist: lxml>=4.6.0
Provides-Extra: dev
Requires-Dist: pytest>=7.0.0; extra == "dev"
Requires-Dist: pytest-cov>=3.0.0; extra == "dev"
Requires-Dist: black>=22.0.0; extra == "dev"
Requires-Dist: flake8>=4.0.0; extra == "dev"
Requires-Dist: mypy>=0.950; extra == "dev"
Dynamic: license-file
